{"Knows": {"WallJump": [false, 0], "ShineSpark": [false, 0], "MidAirMorph": [false, 0], "CrouchJump": [false, 0], "Mockball": [true, 5], "SimpleShortCharge": [true, 5], "InfiniteBombJump": [true, 1], "GreenGateGlitch": [true, 5], "ShortCharge": [true, 10], "GravityJump": [true, 1], "SpringBallJump": [true, 5], "SpringBallJumpFromWall": [false, 0], "GetAroundWallJump": [true, 5], "DraygonGrappleKill": [true, 1], "DraygonSparkKill": [false, 0], "MicrowaveDraygon": [true, 1], "MicrowavePhantoon": [true, 1], "IceZebSkip": [true, 10], "SpeedZebSkip": [false, 0], "HiJumpMamaTurtle": [true, 1], "GravLessLevel1": [true, 5], "GravLessLevel2": [false, 0], "GravLessLevel3": [false, 0], "CeilingDBoost": [true, 1], "BillyMays": [true, 1], "AlcatrazEscape": [true, 1], "ReverseGateGlitch": [true, 5], "ReverseGateGlitchHiJumpLess": [true, 10], "EarlyKraid": [true, 1], "XrayDboost": [false, 0], "XrayIce": [false, 0], "RedTowerClimb": [true, 10], "RonPopeilScrew": [true, 5], "OldMBWithSpeed": [false, 0], "Moondance": [false, 0], "HiJumpLessGauntletAccess": [true, 5], "HiJumpGauntletAccess": [true, 5], "LowGauntlet": [false, 0], "IceEscape": [false, 0], "WallJumpCathedralExit": [true, 1], "BubbleMountainWallJump": [true, 1], "NovaBoost": [false, 0], "NorfairReserveDBoost": [true, 5], "CrocPBsDBoost": [false, 0], "CrocPBsIce": [true, 5], "IceMissileFromCroc": [false, 0], "FrogSpeedwayWithoutSpeed": [true, 1], "LavaDive": [true, 5], "LavaDiveNoHiJump": [false, 0], "WorstRoomIceCharge": [false, 0], "WorstRoomWallJump": [false, 0], "ScrewAttackExit": [true, 1], "ScrewAttackExitWithoutScrew": [true, 5], "FirefleasWalljump": [true, 1], "DodgeLowerNorfairEnemies": [false, 0], "ContinuousWallJump": [false, 0], "DiagonalBombJump": [false, 0], "MockballWs": [true, 5], "SpongeBathBombJump": [false, 0], "SpongeBathHiJump": [true, 1], "SpongeBathSpeed": [true, 1], "TediousMountEverest": [false, 0], "DoubleSpringBallJump": [false, 0], "BotwoonToDraygonWithIce": [false, 0], "DraygonRoomGrappleExit": [false, 0], "DraygonRoomCrystalFlash": [false, 0], "PreciousRoomXRayExit": [false, 0], "MochtroidClip": [true, 1], "PuyoClip": [true, 10], "PuyoClipXRay": [false, 0], "SnailClip": [false, 0], "SuitlessPuyoClip": [false, 0], "CrystalFlashClip": [false, 0], "SuitlessCrystalFlashClip": [false, 0], "KillPlasmaPiratesWithSpark": [false, 0], "KillPlasmaPiratesWithCharge": [true, 1], "AccessSpringBallWithHiJump": [true, 1], "AccessSpringBallWithSpringBallBombJumps": [true, 5], "AccessSpringBallWithBombJumps": [false, 0], "AccessSpringBallWithSpringBallJump": [false, 0], "AccessSpringBallWithXRayClimb": [false, 0], "AccessSpringBallWithGravJump": [true, 1], "AccessSpringBallWithFlatley": [false, 0]}, "Settings": {"Ice": "Bring the heat", "MainUpperNorfair": "Bring the heat", "LowerNorfair": "Default", "Kraid": "Quick Kill", "Phantoon": "No problemo", "Draygon": "No problemo", "Ridley": "Used to it", "MotherBrain": "Is this really the last boss?", "X-Ray": "Default", "Gauntlet": "Default"}, "Controller": {"A": "Dash", "B": "Jump", "X": "Item Cancel", "Y": "Shoot", "L": "Angle Down", "R": "Angle Up", "Select": "Item Select", "Moonwalk": true}, "password": "dec1da56ede3fb487e2cd5d7233dbf7360d385328f4d40a85f11bcb2e4bf9d20", "score": 259}